cyc_pep_perm/__init__.py
cyc_pep_perm/__main__.py
cyc_pep_perm/api.py
cyc_pep_perm/cli.py
cyc_pep_perm/py.typed
cyc_pep_perm/version.py
cyc_pep_perm/data/__init__.py
cyc_pep_perm/data/descriptors.py
cyc_pep_perm/data/paths.py
cyc_pep_perm/data/processing.py
cyc_pep_perm/models/__init__.py
cyc_pep_perm/models/randomforest.py
cyc_pep_perm/models/randomforest_class.py
cyc_pep_perm/models/xgboost.py
cyc_pep_perm-0.1.2.dist-info/LICENSE
cyc_pep_perm-0.1.2.dist-info/METADATA
cyc_pep_perm-0.1.2.dist-info/WHEEL
cyc_pep_perm-0.1.2.dist-info/entry_points.txt
cyc_pep_perm-0.1.2.dist-info/top_level.txt
cyc_pep_perm-0.1.2.dist-info/RECORD
