Metadata-Version: 2.1
Name: cyc_pep_perm
Version: 0.1.2
Summary: Python package to predict membrane permeability of cyclic peptides.
Home-page: https://github.com/schwallergroup/CycPepPerm
Download-URL: https://github.com/schwallergroup/CycPepPerm/releases
Author: Rebecca M Neeser
Author-email: rebecca.neeser@epfl.ch
Maintainer: Rebecca M Neeser
Maintainer-email: rebecca.neeser@epfl.ch
License: MIT
Project-URL: Tracker, https://github.com/schwallergroup/CycPepPerm/issues
Project-URL: Source, https://github.com/schwallergroup/CycPepPerm
Project-URL: Documentation, https://cyc_pep_perm.readthedocs.io
Keywords: snekpack,cookiecutter,chemistry,ai,ml,deep-learning
Classifier: Development Status :: 1 - Planning
Classifier: Environment :: Console
Classifier: Intended Audience :: Developers
Classifier: License :: OSI Approved :: MIT License
Classifier: Operating System :: OS Independent
Classifier: Framework :: Pytest
Classifier: Framework :: tox
Classifier: Framework :: Sphinx
Classifier: Programming Language :: Python
Classifier: Programming Language :: Python :: 3.8
Classifier: Programming Language :: Python :: 3 :: Only
Classifier: Topic :: Scientific/Engineering :: Chemistry
Classifier: Topic :: Scientific/Engineering :: Artificial Intelligence
Classifier: Topic :: Scientific/Engineering :: Physics
Requires-Python: >=3.8
License-File: LICENSE
Requires-Dist: tox
Requires-Dist: more-itertools
Requires-Dist: tqdm
Requires-Dist: click
Requires-Dist: more-click
Requires-Dist: pandas
Requires-Dist: numpy
Requires-Dist: scikit-learn==1.0.2
Requires-Dist: mordred
Requires-Dist: rdkit
Requires-Dist: pandas-ods-reader
Requires-Dist: xgboost
Requires-Dist: shap
Requires-Dist: matplotlib
Provides-Extra: docs
Requires-Dist: sphinx; extra == "docs"
Requires-Dist: sphinx-rtd-theme; extra == "docs"
Requires-Dist: sphinx-click; extra == "docs"
Requires-Dist: sphinx-automodapi; extra == "docs"
Provides-Extra: tests
Requires-Dist: pytest; extra == "tests"
Requires-Dist: coverage; extra == "tests"
